pyphihue/__init__.py
pyphihue/bridge.py
pyphihue/light.py
pyphihue-0.2.5.dist-info/DESCRIPTION.rst
pyphihue-0.2.5.dist-info/METADATA
pyphihue-0.2.5.dist-info/RECORD
pyphihue-0.2.5.dist-info/WHEEL
pyphihue-0.2.5.dist-info/metadata.json
pyphihue-0.2.5.dist-info/top_level.txt
