Metadata-Version: 2.0
Name: pyphihue
Version: 0.2.5
Summary: A library to interface with Philips Hue
Home-page: https://gitlab.com/pyphihue/pyphihue
Author: Patrick Scholten
Author-email: pydevpat@gmail.com
License: MIT
Download-URL: https://gitlab.com/pyphihue/pyphihue/repository/archive.tar.gz?ref=master
Keywords: Philips Hue API-wrapper
Platform: UNKNOWN
Classifier: Development Status :: 4 - Beta
Classifier: Intended Audience :: Developers
Classifier: Topic :: Home Automation
Classifier: License :: OSI Approved :: MIT License
Classifier: Programming Language :: Python :: 3.6
Requires-Dist: requests
